surfinFBA/Surfin_FBA.py
surfinFBA/__init__.py
surfinFBA/call_me.py
surfinFBA/examples/.DS_Store
surfinFBA/examples/gurobi.log
surfinFBA/examples/model_file_info.txt
surfinFBA/examples/real_model_examples.py
surfinFBA/examples/real_model_log.txt
surfinFBA/examples/toy_model_examples.py
surfinFBA/examples/sample_models/1221522.3.json
surfinFBA/examples/sample_models/351746.6.json
surfinFBA/examples/sample_models/53408.6.json
surfinFBA/examples/sample_models/548.154.json
surfinFBA/examples/sample_models/587753.10.json
surfinFBA/examples/sample_models/587753.25.json
surfinFBA/examples/sample_models/615.102.json
surfinFBA/examples/sample_models/76761.16.json
surfinFBA/examples/sample_models/iND750.json
surfinFBA/examples/sample_models/iRC1080.json
surfinFBA/oldschool_dfba/__init__.py
surfinFBA/oldschool_dfba/oldschool_dfba.py
surfinFBA-0.9.0.dist-info/LICENSE
surfinFBA-0.9.0.dist-info/METADATA
surfinFBA-0.9.0.dist-info/WHEEL
surfinFBA-0.9.0.dist-info/top_level.txt
surfinFBA-0.9.0.dist-info/RECORD
