Metadata-Version: 2.1
Name: surfinFBA
Version: 0.9.0
Summary: Dynamic FBA for use with COBRApy metabolic models
Home-page: https://github.com/jdbrunner/surfin_fba
Author: James D. Brunner, Ph.D.
Author-email: brunner.james@mayo.edu
License: UNKNOWN
Platform: UNKNOWN
Classifier: Programming Language :: Python :: 3
Classifier: License :: OSI Approved :: MIT License
Classifier: Operating System :: OS Independent
Requires-Python: >=3.6
